{
  "cover": "/cover/SR.jpg",
  "name": "Shamrock no Hanakotoba",
  "dev": "Dolce/More",
  "date": "28/09/2018",
  "des": "Kouko nghe được tin đồn rằng bạn thân cô ấy, Nanaka, thường xuất hiện cùng nhiều gã đàn ông lạ mặt. Tuy nhiên, Nanaka đã phủ nhận tất cả và bỏ đi khi bị hỏi đến.<br /><br />Lo lắng cho người bạn của mình, Kouko đã bắt đầu đi điều tra. Thế nhưng, chính Kouko lại bị lôi kéo vào hoạt động tương tự. Tệ hơn, điều mà Kouko phát hiện ra là Nanaka đang bị mê hoặc bởi gã đàn ông đã từng lợi dụng mình. Và hai người bạn khác của cô ấy là Matsuri và Aki cũng bị cuốn vào vòng xoáy tệ nạn đó...",
  "game": "",
  "patch": "",
  "vid": "",
  "image": [{ "image": "/image/SR1.jpg" }]
}
